jamespopcat.py
jamespopcat-1.0.3.dist-info/LICENSE.txt
jamespopcat-1.0.3.dist-info/METADATA
jamespopcat-1.0.3.dist-info/WHEEL
jamespopcat-1.0.3.dist-info/top_level.txt
jamespopcat-1.0.3.dist-info/RECORD
