Metadata-Version: 2.1
Name: jamespopcat
Version: 1.0.3
Summary: Auto clicker Popcat
Author: CTRCRK
Author-email: ctrcrk.id@gmail.com
License: Apache License 2.0
License-File: LICENSE.txt
Requires-Dist: selenium
Requires-Dist: psutil
